pontis/admin/__init__.py
pontis/admin/client.py
pontis/core/__init__.py
pontis/core/base_client.py
pontis/core/client.py
pontis/core/const.py
pontis/core/entry.py
pontis/core/utils.py
pontis/core/abi/Account.json
pontis/core/abi/ERC20.json
pontis/publisher/__init__.py
pontis/publisher/assets.py
pontis/publisher/client.py
pontis/publisher/fetch/__init__.py
pontis/publisher/fetch/bitstamp.py
pontis/publisher/fetch/cex.py
pontis/publisher/fetch/coinbase.py
pontis/publisher/fetch/coingecko.py
pontis/publisher/fetch/cryptowatch.py
pontis/publisher/fetch/ftx.py
pontis/publisher/fetch/gemini.py
pontis/publisher/fetch/thegraph.py
pontis-0.6.3.dist-info/METADATA
pontis-0.6.3.dist-info/WHEEL
pontis-0.6.3.dist-info/top_level.txt
pontis-0.6.3.dist-info/RECORD
