Metadata-Version: 2.1
Name: pontis
Version: 0.6.3
Summary: Core package for Pontis oracle on Starknet
Home-page: https://github.com/42labs/Pontis
Author: Jonas Nelle
Author-email: jonas.a.nelle@gmail.com
Classifier: Programming Language :: Python :: 3
Classifier: License :: OSI Approved :: MIT License
Classifier: Operating System :: OS Independent
Requires-Python: ==3.7.*
Requires-Dist: starknet.py
Requires-Dist: ecdsa
Requires-Dist: fastecdsa
Requires-Dist: cairo-lang
Requires-Dist: cairo-nile
